hf_vram_calc/__init__.py
hf_vram_calc/calculator.py
hf_vram_calc/cli.py
hf_vram_calc/config.py
hf_vram_calc/data_types.json
hf_vram_calc/display_settings.json
hf_vram_calc/gpu_types.json
hf_vram_calc/models.py
hf_vram_calc/parallel.py
hf_vram_calc/parser.py
hf_vram_calc-1.0.9.dist-info/METADATA
hf_vram_calc-1.0.9.dist-info/WHEEL
hf_vram_calc-1.0.9.dist-info/entry_points.txt
hf_vram_calc-1.0.9.dist-info/RECORD
