Metadata-Version: 2.4
Name: hf-vram-calc
Version: 1.0.9
Summary: GPU memory calculator for Hugging Face models with different data types and parallelization strategies
Project-URL: Homepage, https://github.com/example/hf-vram-calc
Project-URL: Repository, https://github.com/example/hf-vram-calc
Project-URL: Issues, https://github.com/example/hf-vram-calc/issues
Author-email: HF VRAM Calculator Contributors <hf-vram-calc@example.com>
License: MIT
Keywords: ai,calculator,gpu,huggingface,memory,ml,transformer,vram
Classifier: Development Status :: 4 - Beta
Classifier: Intended Audience :: Developers
Classifier: Intended Audience :: Science/Research
Classifier: License :: OSI Approved :: MIT License
Classifier: Operating System :: OS Independent
Classifier: Programming Language :: Python :: 3
Classifier: Programming Language :: Python :: 3.8
Classifier: Programming Language :: Python :: 3.9
Classifier: Programming Language :: Python :: 3.10
Classifier: Programming Language :: Python :: 3.11
Classifier: Programming Language :: Python :: 3.12
Classifier: Topic :: Scientific/Engineering :: Artificial Intelligence
Classifier: Topic :: Software Development :: Libraries :: Python Modules
Classifier: Topic :: System :: Hardware
Requires-Python: >=3.8
Requires-Dist: accelerate>=0.20.0
Requires-Dist: requests>=2.25.0
Requires-Dist: rich>=13.0.0
Requires-Dist: torch>=1.9.0
Requires-Dist: transformers>=4.20.0
Provides-Extra: dev
Requires-Dist: black>=22.0.0; extra == 'dev'
Requires-Dist: flake8>=4.0.0; extra == 'dev'
Requires-Dist: isort>=5.0.0; extra == 'dev'
Requires-Dist: pytest>=7.0.0; extra == 'dev'
